wagtailflags/__init__.py
wagtailflags/apps.py
wagtailflags/conditions.py
wagtailflags/forms.py
wagtailflags/signals.py
wagtailflags/utils.py
wagtailflags/views.py
wagtailflags/wagtail_hooks.py
wagtailflags/static/wagtailflags/css/wagtailflags.css
wagtailflags/templates/wagtailflags/flag.svg
wagtailflags/templates/wagtailflags/index.html
wagtailflags/templates/wagtailflags/flags/create_flag.html
wagtailflags/templates/wagtailflags/flags/delete_condition.html
wagtailflags/templates/wagtailflags/flags/delete_flag.html
wagtailflags/templates/wagtailflags/flags/edit_condition.html
wagtailflags/templates/wagtailflags/flags/flag_index.html
wagtailflags/templates/wagtailflags/includes/flag_breadcrumbs.html
wagtailflags/templates/wagtailflags/includes/flag_header.html
wagtailflags/templates/wagtailflags/includes/flag_index.html
wagtailflags/templates/wagtailflags/includes/header.html
wagtailflags/templatetags/__init__.py
wagtailflags/templatetags/wagtailflags_admin.py
wagtailflags/tests/__init__.py
wagtailflags/tests/settings.py
wagtailflags/tests/test_apps.py
wagtailflags/tests/test_conditions.py
wagtailflags/tests/test_signals.py
wagtailflags/tests/test_templatetags_wagtailflags_admin.py
wagtailflags/tests/test_views.py
wagtailflags/tests/urls.py
wagtail_flags-5.3.1.dist-info/LICENSE
wagtail_flags-5.3.1.dist-info/METADATA
wagtail_flags-5.3.1.dist-info/WHEEL
wagtail_flags-5.3.1.dist-info/top_level.txt
wagtail_flags-5.3.1.dist-info/RECORD
