Metadata-Version: 2.1
Name: wagtail-flags
Version: 5.3.1
Summary: Feature flags for Wagtail sites
Author-email: CFPB <tech@cfpb.gov>
License: CC0
Project-URL: Homepage, https://github.com/cfpb/wagtail-flags
Project-URL: Bug Reports, https://github.com/cfpb/wagtail-flags/issues
Project-URL: Source, https://github.com/cfpb/wagtail-flags
Classifier: Framework :: Django
Classifier: Framework :: Django :: 3.2
Classifier: Framework :: Django :: 4
Classifier: Framework :: Wagtail
Classifier: Framework :: Wagtail :: 4
Classifier: License :: CC0 1.0 Universal (CC0 1.0) Public Domain Dedication
Classifier: License :: Public Domain
Classifier: Programming Language :: Python
Classifier: Programming Language :: Python :: 3
Requires-Python: >=3.8
License-File: LICENSE
Requires-Dist: wagtail >=4
Requires-Dist: django-flags >4.2
Provides-Extra: testing
Requires-Dist: coverage[toml] ; extra == 'testing'
